SMdRQA/Extract_from_RP.py
SMdRQA/RP_maker.py
SMdRQA/RP_maker_diagnose.py
SMdRQA/RQA2.py
SMdRQA/RQA_functions.py
SMdRQA/__init__.py
SMdRQA/cross_validation.py
SMdRQA/nl_tests.py
SMdRQA/utils.py
SMdRQA/window_size.py
SMdRQA/tests/__init__.py
SMdRQA/tests/test_RQA2.py
SMdRQA/tests/test_RQA_functions.py
SMdRQA/tests/test_utils.py
smdrqa-2025.7.27.dist-info/AUTHORS.rst
smdrqa-2025.7.27.dist-info/LICENSE
smdrqa-2025.7.27.dist-info/METADATA
smdrqa-2025.7.27.dist-info/WHEEL
smdrqa-2025.7.27.dist-info/top_level.txt
smdrqa-2025.7.27.dist-info/RECORD
