Metadata-Version: 2.1
Name: SMdRQA
Version: 2025.7.27
Summary: A Python implementation of MdRQA
Home-page: https://github.com/SwaragThaikkandi/Sliding_MdRQA
Author: Swarag Thaikkandi, K.M. Sharika, Miss Nivedita
Author-email: tsk4at@gmail.com
Classifier: Programming Language :: Python :: 3.9
Classifier: Programming Language :: Python :: 3.10
Classifier: Programming Language :: Python :: 3.11
Classifier: Intended Audience :: Science/Research
Classifier: Topic :: Scientific/Engineering
Classifier: License :: OSI Approved :: GNU General Public License v3 (GPLv3)
Classifier: Operating System :: OS Independent
Requires-Python: >=3.6
License-File: LICENSE
License-File: AUTHORS.rst
Requires-Dist: numpy
Requires-Dist: scipy
Requires-Dist: operator-courier
Requires-Dist: contextlib2
Requires-Dist: pytest-warnings
Requires-Dist: matplotlib
Requires-Dist: pandas
Requires-Dist: tqdm
Requires-Dist: memory-profiler
Requires-Dist: kuramoto
Requires-Dist: networkx
Requires-Dist: p-tqdm
Requires-Dist: numba
